rapid_models/__init__.py
rapid_models/rapid_models.py
rapid_models/doe/__init__.py
rapid_models/doe/adaptive_learning.py
rapid_models/doe/utils.py
rapid_models/gp_diagnostics/__init__.py
rapid_models/gp_diagnostics/cv.py
rapid_models/gp_diagnostics/metrics.py
rapid_models/gp_diagnostics/utils/__init__.py
rapid_models/gp_diagnostics/utils/checks.py
rapid_models/gp_diagnostics/utils/linalg.py
rapid_models/gp_diagnostics/utils/stats.py
rapid_models/gp_diagnostics_plots/__init__.py
rapid_models/gp_models/__init__.py
rapid_models/gp_models/templates.py
rapid_models/gp_models/utils.py
rapid_models/preprocessing/__init__.py
rapid_models/preprocessing/scalers.py
rapid_models-0.1.7.dist-info/AUTHORS.rst
rapid_models-0.1.7.dist-info/LICENSE
rapid_models-0.1.7.dist-info/METADATA
rapid_models-0.1.7.dist-info/WHEEL
rapid_models-0.1.7.dist-info/entry_points.txt
rapid_models-0.1.7.dist-info/top_level.txt
rapid_models-0.1.7.dist-info/RECORD
