Metadata-Version: 2.1
Name: rapid-models
Version: 0.1.7
Summary: Python package (Reciprocal Data and Physics models - RaPiD-models) to support more specific, accurate and timely decision support in operation of safety-critical systems, by combining physics-based modelling with data-driven machine learning and probabilistic uncertainty assessment.
Home-page: https://github.com/RaPiD-models/rapid_models
Download-URL: https://github.com/RaPiD-models/rapid_models/archive/refs/tags/v0.1.7.tar.gz
Author: Simen Eldevik
Author-email: simen.eldevik@dnv.com
License: GNU General Public License v3
Keywords: rapid_models
Classifier: Development Status :: 2 - Pre-Alpha
Classifier: Intended Audience :: Developers
Classifier: License :: OSI Approved :: GNU General Public License v3 (GPLv3)
Classifier: Natural Language :: English
Classifier: Programming Language :: Python :: 3
Classifier: Programming Language :: Python :: 3.7
Classifier: Programming Language :: Python :: 3.8
Requires-Python: >=3.6
License-File: LICENSE
License-File: AUTHORS.rst
Requires-Dist: pyDOE2
Requires-Dist: numpy
Requires-Dist: scipy
Requires-Dist: scikit-learn
Requires-Dist: torch (>=1.10.0)
Requires-Dist: gpytorch (>=1.6.0)
Requires-Dist: nptyping
